papaprice/__init__.py
papaprice/etmall.py
papaprice/momo.py
papaprice/papaprice.py
papaprice/pchome.py
papaprice/shopee.py
papaprice/yahoo.py
papaprice-0.0.6.dist-info/LICENSE
papaprice-0.0.6.dist-info/METADATA
papaprice-0.0.6.dist-info/WHEEL
papaprice-0.0.6.dist-info/top_level.txt
papaprice-0.0.6.dist-info/RECORD
