Metadata-Version: 2.1
Name: papaprice
Version: 0.0.6
Summary: crawl the name and price of each product from e-commerce websites in Taiwan.
Home-page: https://github.com/chinchillaLiao/papaprice
Author: GaryLiao
Author-email: chinchillaliao@gmail.com
License: MIT
Platform: UNKNOWN
Classifier: Programming Language :: Python :: 3
Classifier: License :: OSI Approved :: MIT License
Classifier: Operating System :: OS Independent
Requires-Python: >=3.6
Requires-Dist: requests
Requires-Dist: bs4
Requires-Dist: js2py
